pynetstat.py
setup.py
pynetstat.egg-info/PKG-INFO
pynetstat.egg-info/SOURCES.txt
pynetstat.egg-info/dependency_links.txt
pynetstat.egg-info/pynetstat.py
pynetstat.egg-info/top_level.txt