Metadata-Version: 1.0
Name: pynetstat
Version: 0.2.0
Summary: python module parse netstat command output into list of namedtuple:inet_connection
Home-page: http://www.iesensor.com/blog/2012/12/11/pynetstat/
Author: Qingfeng Xia
Author-email: Qingfeng.Xia[]gmail.com
License: BSD
Platform: any
Classifier: Development Status :: 4 - Beta
Classifier: Intended Audience :: Developers
Classifier: License :: OSI Approved :: BSD License
Classifier: Programming Language :: Python
Classifier: Environment :: Console
Classifier: Intended Audience :: System Administrators
Classifier: Topic :: Software Development :: Libraries :: Python Modules
Classifier: Topic :: System :: Networking :: Monitoring
Classifier: Operating System :: POSIX
Classifier: Operating System :: Microsoft
